{
  "blogs": [
    {
      "id": 1,
      "title": "想当年我找第一份工作也是花了好大力气",
      "body": "想当年我找第一份工作也是花了好大力气，面试了100多份工作，我一个学动画，后来连博物馆讲解员，足球网站编辑，不知名的剧场的默剧演员都面试过……… :blobsweats:  看到tl上正在找工作的朋友们，祝你们早日找到工作！ :ablobcall:",
      "author": "我们不是机器"
    },
    {
      "id": 2,
      "title": "我是弱智",
      "body": "啊。。。。 玩个多邻国都能卡关 に、が、は分不清楚 我是弱智",
      "author": "白痴月亮先生"
    },
    {
      "id": 3,
      "title": "周耀辉",
      "body": "周耀辉  | 两岁的时候，你的父亲离开了这个家。你在贫民区长大，和妈妈姐姐住在一个十平方的房子，那层楼住了80多户居民，共用一个浴室和洗手间。你说过：“很小就强烈地感觉到妈妈对我的期望，要出人头地。”但是，你的小学时代有很多的时间是在电影院度过的，你的妈妈甚至每天去学校，把看电影所需要的钱交给你。",
      "author": "掘火档案考古机器人"
    },
    {
      "title": "新博客",
      "body": "测试一下post请求",
      "author": "nic",
      "id": 4
    }
  ]
}